[
  {
    "title": "MapleStory x Sunright Tea Livestream",
    "content": "Join Community Manager Veeraah in the next Community Livestream as he showcases the Sunright Tea drinks available now!",
    "time": "5 hours ago",
    "actualDate": "Jan 03, 2024",
    "photo": "https://nxcache.nexon.net/cms/2022/q3/1109/msw-6101-220707-evergreen-generic-livestream-banners-news-post-540x304.png",
    "link": "https://maplestory.nexon.net//news/88796/maplestory-x-sunright-tea-livestream"
  },
  {
    "title": "Cash Shop Update for January 3",
    "content": "Gachapon Update, Premium Surprise Style Box, and more!",
    "time": "5 hours ago",
    "actualDate": "Jan 03, 2024",
    "photo": "https://nxcache.nexon.net/cms/2023/q4/2806/540x304-january-3-cash-shop-update-maplestory.jpg",
    "link": "https://maplestory.nexon.net//news/88481/cash-shop-update-for-january-3"
  },
  {
    "title": "Miracle Winter - January 6 - Tops/Bottoms/Overalls/Capes",
    "content": "On Saturday, January 6, 2024, Maplers on all Worlds will have Miracle Time enabled for Tops, Bottoms, Overalls and Cape Equipment!",
    "time": "1 day ago",
    "actualDate": "1 day ago",
    "photo": "https://nxcache.nexon.net/cms/2023/q4/2794/540x304-miracle-winter-january-6-tops-bottoms-overalls-capes-maplestory.jpg",
    "link": "https://maplestory.nexon.net//news/88470/miracle-winter-january-6-tops-bottoms-overalls-capes"
  },
  {
    "title": "Hang Out with MapleStory at Sunright Tea Studio!",
    "content": "Help us launch our collaboration with Sunright Tea Studio. Join us in Los Angeles on Jan. 6!",
    "time": "6 days ago",
    "actualDate": "Dec 28, 2023",
    "photo": "https://nxcache.nexon.net/cms/2023/q4/2621/231227-sunright-tea-x-maplestory-news-post-540x304.png",
    "link": "https://maplestory.nexon.net//news/88286/hang-out-with-maplestory-at-sunright-tea-studio"
  },
  {
    "title": "Cash Shop Update for December 27",
    "content": "Royal Styles, Chunky Cable-Knit Package, Winter Covers, and more!",
    "time": "Dec 26, 2023",
    "actualDate": "Dec 26, 2023",
    "photo": "https://nxcache.nexon.net/cms/2023/q4/2783/540x304-december-27-cash-shop-update-maplestory.jpg",
    "link": "https://maplestory.nexon.net//news/88317/cash-shop-update-for-december-27"
  },
  {
    "title": "December 2023 Community Contests and Events",
    "content": "Take a look at the new and upcoming Community Contests below, and be prepared to test your imagination!",
    "time": "Dec 22, 2023",
    "actualDate": "Dec 22, 2023",
    "photo": "https://nxcache.nexon.net/cms/2023/q4/2003/210406_540x304_communitycontests.jpg",
    "link": "https://maplestory.nexon.net//news/88689/december-2023-community-contests-and-events"
  }
]
