[
  {
    "title": " Miracle Winter - January 13 - Shoes",
    "content": "On Saturday, January 13, 2024, Maplers on all Worlds will have Miracle Time enabled for Shoe Equipment!",
    "time": "14 hours ago ",
    "actualDate": "Jan 09, 2024",
    "photo": "https://nxcache.nexon.net/cms/2023/q4/2801/540x304-miracle-winter-january-13-shoe-equipment-maplestory.jpg)",
    "link": "https://maplestory.nexon.net/https://maplestory.nexon.net//news/88712/miracle-winter-january-13-shoes"
  },
  {
    "title": " [Updated December 20] v.247 - New Age: Into the Abyss Patch Notes",
    "content": "Click here to read the patch notes for v.247 - New Age: Into the Abyss.",
    "time": "Dec 12, 2023 ",
    "actualDate": "Dec 12, 2023 ",
    "photo": "https://nxcache.nexon.net/cms/2023/q4/2392/231208-wgc-533-ms-newage-pt2-patchnotes-540x304.png)",
    "link": "https://maplestory.nexon.net/https://maplestory.nexon.net//news/87688/updated-december-20-v-247-new-age-into-the-abyss-patch-notes"
  }
]
